{"issue_url": "https://api.github.com/repos/rails/rails/issues/8918", "repo": "rails", "body": "In this case I dont understand the naming convention. Shouldn't it be at oeast an alias to maintain consistent API?  \r\n\r\n--  \r\nJakub Arnold\r\n\r\n\r\nOn Sunday 13 January 2013 at 17:50, Steve Klabnik wrote:\r\n\r\n> Yes, it is.\r\n>  \r\n> \u2014\r\n> Reply to this email directly or view it on GitHub (https://github.com/rails/rails/pull/8918#issuecomment-12196158).  \r\n>  \r\n>  \r\n>  ", "_id": {"$oid": "5237ee9bbd3543c151009fd6"}, "issue_id": 8918, "url": "https://api.github.com/repos/rails/rails/issues/comments/12196326", "html_url": "https://github.com/rails/rails/pull/8918#issuecomment-12196326", "updated_at": "2013-01-13T17:00:59Z", "user": {"subscriptions_url": "https://api.github.com/users/darthdeus/subscriptions", "events_url": "https://api.github.com/users/darthdeus/events{/privacy}", "repos_url": "https://api.github.com/users/darthdeus/repos", "gists_url": "https://api.github.com/users/darthdeus/gists{/gist_id}", "url": "https://api.github.com/users/darthdeus", "login": "darthdeus", "gravatar_id": "16a5eec5eca4550033c0e19dba3b32b8", "html_url": "https://github.com/darthdeus", "following_url": "https://api.github.com/users/darthdeus/following{/other_user}", "received_events_url": "https://api.github.com/users/darthdeus/received_events", "organizations_url": "https://api.github.com/users/darthdeus/orgs", "avatar_url": "https://2.gravatar.com/avatar/16a5eec5eca4550033c0e19dba3b32b8?d=https%3A%2F%2Fidenticons.github.com%2F1996a22474064a8fefda6b29a77112ff.png", "starred_url": "https://api.github.com/users/darthdeus/starred{/owner}{/repo}", "id": 123374, "followers_url": "https://api.github.com/users/darthdeus/followers", "type": "User"}, "created_at": "2013-01-13T17:00:59Z", "id": 12196326, "owner": "rails"}
