{"issue_url": "https://api.github.com/repos/rails/rails/issues/1130", "repo": "rails", "body": "Just wanted to put my vote here for this functionality. I tried to use coffeescript in an xhr request but it didn't work. Great that it'll probably be in 3.2 so for now I'll go grab the gem by markbates. Thanks!", "_id": {"$oid": "52385d08bd3543c151011f7f"}, "issue_id": 1130, "url": "https://api.github.com/repos/rails/rails/issues/comments/1248951", "html_url": "https://github.com/rails/rails/pull/1130#issuecomment-1248951", "updated_at": "2011-05-27T13:09:18Z", "user": {"subscriptions_url": "https://api.github.com/users/JeanMertz/subscriptions", "events_url": "https://api.github.com/users/JeanMertz/events{/privacy}", "repos_url": "https://api.github.com/users/JeanMertz/repos", "gists_url": "https://api.github.com/users/JeanMertz/gists{/gist_id}", "url": "https://api.github.com/users/JeanMertz", "login": "JeanMertz", "gravatar_id": "39fc02d6a812edf6daa8914247e9b4c0", "html_url": "https://github.com/JeanMertz", "following_url": "https://api.github.com/users/JeanMertz/following{/other_user}", "received_events_url": "https://api.github.com/users/JeanMertz/received_events", "organizations_url": "https://api.github.com/users/JeanMertz/orgs", "avatar_url": "https://1.gravatar.com/avatar/39fc02d6a812edf6daa8914247e9b4c0?d=https%3A%2F%2Fidenticons.github.com%2F42c97ca1e78226af770f9b7a8625c74a.png", "starred_url": "https://api.github.com/users/JeanMertz/starred{/owner}{/repo}", "id": 383250, "followers_url": "https://api.github.com/users/JeanMertz/followers", "type": "User"}, "created_at": "2011-05-27T13:09:18Z", "id": 1248951, "owner": "rails"}
