{"issue_url": "https://api.github.com/repos/rails/rails/issues/10812", "repo": "rails", "body": "We just shipped 4.0 and it'll be a while before 4.1 so now's the time to do it. I also went back to the original Trac report to see why it was added and it turns out it was to test that irregular inflections cope where words start with different letters.", "_id": {"$oid": "5237db8dbd3543c15100888b"}, "issue_id": 10812, "url": "https://api.github.com/repos/rails/rails/issues/comments/21860973", "html_url": "https://github.com/rails/rails/pull/10812#issuecomment-21860973", "updated_at": "2013-07-31T13:13:50Z", "user": {"subscriptions_url": "https://api.github.com/users/pixeltrix/subscriptions", "events_url": "https://api.github.com/users/pixeltrix/events{/privacy}", "repos_url": "https://api.github.com/users/pixeltrix/repos", "gists_url": "https://api.github.com/users/pixeltrix/gists{/gist_id}", "url": "https://api.github.com/users/pixeltrix", "login": "pixeltrix", "gravatar_id": "b14001f2b40640dd6cb63f0e8f1f4869", "html_url": "https://github.com/pixeltrix", "following_url": "https://api.github.com/users/pixeltrix/following{/other_user}", "received_events_url": "https://api.github.com/users/pixeltrix/received_events", "organizations_url": "https://api.github.com/users/pixeltrix/orgs", "avatar_url": "https://0.gravatar.com/avatar/b14001f2b40640dd6cb63f0e8f1f4869?d=https%3A%2F%2Fidenticons.github.com%2F7cb36e23529e4de4c41460940cc85e6e.png", "starred_url": "https://api.github.com/users/pixeltrix/starred{/owner}{/repo}", "id": 6321, "followers_url": "https://api.github.com/users/pixeltrix/followers", "type": "User"}, "created_at": "2013-07-31T13:13:50Z", "id": 21860973, "owner": "rails"}
