{"issue_url": "https://api.github.com/repos/rails/rails/issues/3762", "repo": "rails", "body": "We already had a gem like that. Btw, are sure the address issue is a inflection one? I think rails infects it correctly and the problem is in the serialization, no?", "_id": {"$oid": "52383206bd3543c15100f83b"}, "issue_id": 3762, "url": "https://api.github.com/repos/rails/rails/issues/comments/2886714", "html_url": "https://github.com/rails/rails/pull/3762#issuecomment-2886714", "updated_at": "2011-11-27T09:08:32Z", "user": {"subscriptions_url": "https://api.github.com/users/josevalim/subscriptions", "events_url": "https://api.github.com/users/josevalim/events{/privacy}", "repos_url": "https://api.github.com/users/josevalim/repos", "gists_url": "https://api.github.com/users/josevalim/gists{/gist_id}", "url": "https://api.github.com/users/josevalim", "login": "josevalim", "gravatar_id": "e837f6b7fd146ab16ed3d663476c063e", "html_url": "https://github.com/josevalim", "following_url": "https://api.github.com/users/josevalim/following{/other_user}", "received_events_url": "https://api.github.com/users/josevalim/received_events", "organizations_url": "https://api.github.com/users/josevalim/orgs", "avatar_url": "https://0.gravatar.com/avatar/e837f6b7fd146ab16ed3d663476c063e?d=https%3A%2F%2Fidenticons.github.com%2Fe20b21ae6508f22fc189c60a0880d0b8.png", "starred_url": "https://api.github.com/users/josevalim/starred{/owner}{/repo}", "id": 9582, "followers_url": "https://api.github.com/users/josevalim/followers", "type": "User"}, "created_at": "2011-11-27T09:08:32Z", "id": 2886714, "owner": "rails"}
