{"updated_at": "2012-01-27T19:34:15Z", "repo": "rails", "created_at": "2012-01-27T19:34:15Z", "owner": "rails", "url": "https://api.github.com/repos/rails/rails/issues/comments/3692720", "id": 3692720, "issue_url": "https://api.github.com/repos/rails/rails/issues/4728", "issue_id": 4728, "user": {"repos_url": "https://api.github.com/users/railsaholic/repos", "type": "User", "html_url": "https://github.com/railsaholic", "starred_url": "https://api.github.com/users/railsaholic/starred{/owner}{/repo}", "subscriptions_url": "https://api.github.com/users/railsaholic/subscriptions", "following_url": "https://api.github.com/users/railsaholic/following{/other_user}", "gravatar_id": "be0d7458f833e45ebef564ac4c378a41", "organizations_url": "https://api.github.com/users/railsaholic/orgs", "url": "https://api.github.com/users/railsaholic", "gists_url": "https://api.github.com/users/railsaholic/gists{/gist_id}", "avatar_url": "https://2.gravatar.com/avatar/be0d7458f833e45ebef564ac4c378a41?d=https%3A%2F%2Fidenticons.github.com%2F8a59a557640d9947954ab305e08ad8a5.png", "id": 304184, "events_url": "https://api.github.com/users/railsaholic/events{/privacy}", "login": "railsaholic", "received_events_url": "https://api.github.com/users/railsaholic/received_events", "followers_url": "https://api.github.com/users/railsaholic/followers"}, "body": "@vijaydev I am sorry but there was some problem with my fork so had to delete them, reopen the PR.", "_id": {"$oid": "52382217bd3543c15100ea49"}, "html_url": "https://github.com/rails/rails/pull/4728#issuecomment-3692720"}
