{"issue_url": "https://api.github.com/repos/rails/rails/issues/3826", "repo": "rails", "body": "I have not been able to spend any time on it last month and I'm in a crunch for at least one more week. If you want to pick it up and rebase it to get it back up to spec", "_id": {"$oid": "52383124bd3543c15100f700"}, "issue_id": 3826, "url": "https://api.github.com/repos/rails/rails/issues/comments/5646281", "html_url": "https://github.com/rails/rails/pull/3826#issuecomment-5646281", "updated_at": "2012-05-11T08:41:29Z", "user": {"subscriptions_url": "https://api.github.com/users/yopefonic/subscriptions", "events_url": "https://api.github.com/users/yopefonic/events{/privacy}", "repos_url": "https://api.github.com/users/yopefonic/repos", "gists_url": "https://api.github.com/users/yopefonic/gists{/gist_id}", "url": "https://api.github.com/users/yopefonic", "login": "yopefonic", "gravatar_id": "d644618e5b64503c1f5e5465cf9f85c1", "html_url": "https://github.com/yopefonic", "following_url": "https://api.github.com/users/yopefonic/following{/other_user}", "received_events_url": "https://api.github.com/users/yopefonic/received_events", "organizations_url": "https://api.github.com/users/yopefonic/orgs", "avatar_url": "https://1.gravatar.com/avatar/d644618e5b64503c1f5e5465cf9f85c1?d=https%3A%2F%2Fidenticons.github.com%2Fbde28ac0b5089d0edb8d904cab610e3e.png", "starred_url": "https://api.github.com/users/yopefonic/starred{/owner}{/repo}", "id": 151257, "followers_url": "https://api.github.com/users/yopefonic/followers", "type": "User"}, "created_at": "2012-05-11T08:41:29Z", "id": 5646281, "owner": "rails"}
