{"body": "Is no one interested in this feature? Should this target the 3-2-stable branch instead of master?", "url": "https://api.github.com/repos/rails/rails/issues/comments/6040406", "created_at": "2012-05-31T16:19:25Z", "html_url": "https://github.com/rails/rails/pull/5969#issuecomment-6040406", "updated_at": "2012-05-31T16:19:25Z", "repo": "rails", "issue_id": 5969, "user": {"following_url": "https://api.github.com/users/hube/following{/other_user}", "events_url": "https://api.github.com/users/hube/events{/privacy}", "organizations_url": "https://api.github.com/users/hube/orgs", "url": "https://api.github.com/users/hube", "gists_url": "https://api.github.com/users/hube/gists{/gist_id}", "html_url": "https://github.com/hube", "subscriptions_url": "https://api.github.com/users/hube/subscriptions", "avatar_url": "https://0.gravatar.com/avatar/89bbf05659f1ac81fb2db5358c53d955?d=https%3A%2F%2Fidenticons.github.com%2F68c150a1032289787b355359af87edc0.png", "repos_url": "https://api.github.com/users/hube/repos", "received_events_url": "https://api.github.com/users/hube/received_events", "gravatar_id": "89bbf05659f1ac81fb2db5358c53d955", "starred_url": "https://api.github.com/users/hube/starred{/owner}{/repo}", "login": "hube", "type": "User", "id": 395901, "followers_url": "https://api.github.com/users/hube/followers"}, "owner": "rails", "_id": {"$oid": "523810b2bd3543c15100d6eb"}, "id": 6040406, "issue_url": "https://api.github.com/repos/rails/rails/issues/5969"}
