{"issue_url": "https://api.github.com/repos/rails/rails/issues/6768", "repo": "rails", "body": "Okay, I got your point, not angry anymore. But as a suggestion, it would be more polite to say something like you just did before closing as this is usually not expected in oss. Something like \"closing for now. Will reopen once the discussed issues are addressed.\"", "_id": {"$oid": "52380449bd3543c15100c59c"}, "issue_id": 6768, "url": "https://api.github.com/repos/rails/rails/issues/comments/6442957", "html_url": "https://github.com/rails/rails/pull/6768#issuecomment-6442957", "updated_at": "2012-06-20T01:26:54Z", "user": {"subscriptions_url": "https://api.github.com/users/rosenfeld/subscriptions", "events_url": "https://api.github.com/users/rosenfeld/events{/privacy}", "repos_url": "https://api.github.com/users/rosenfeld/repos", "gists_url": "https://api.github.com/users/rosenfeld/gists{/gist_id}", "url": "https://api.github.com/users/rosenfeld", "login": "rosenfeld", "gravatar_id": "2abdb50caf0dc5b510330f68b02db8e4", "html_url": "https://github.com/rosenfeld", "following_url": "https://api.github.com/users/rosenfeld/following{/other_user}", "received_events_url": "https://api.github.com/users/rosenfeld/received_events", "organizations_url": "https://api.github.com/users/rosenfeld/orgs", "avatar_url": "https://0.gravatar.com/avatar/2abdb50caf0dc5b510330f68b02db8e4?d=https%3A%2F%2Fidenticons.github.com%2F7c3aa93f86af77d8b1071d5fd2b4c91a.png", "starred_url": "https://api.github.com/users/rosenfeld/starred{/owner}{/repo}", "id": 32246, "followers_url": "https://api.github.com/users/rosenfeld/followers", "type": "User"}, "created_at": "2012-06-20T01:26:54Z", "id": 6442957, "owner": "rails"}
