{"issue_url": "https://api.github.com/repos/rails/rails/issues/6055", "repo": "rails", "body": "```\nirb(main):016:0> Date.today + 1.day\n=> Fri, 13 Jul 2012\nirb(main):017:0> Date.today + 1.day.tap{}\n=> Wed, 31 Jan 2249\n```", "_id": {"$oid": "52380f8dbd3543c15100d546"}, "issue_id": 6055, "url": "https://api.github.com/repos/rails/rails/issues/comments/6949677", "html_url": "https://github.com/rails/rails/pull/6055#issuecomment-6949677", "updated_at": "2012-07-12T22:25:37Z", "user": {"subscriptions_url": "https://api.github.com/users/paneq/subscriptions", "events_url": "https://api.github.com/users/paneq/events{/privacy}", "repos_url": "https://api.github.com/users/paneq/repos", "gists_url": "https://api.github.com/users/paneq/gists{/gist_id}", "url": "https://api.github.com/users/paneq", "login": "paneq", "gravatar_id": "9b81cae1fb43808ac23a2188258ca9e4", "html_url": "https://github.com/paneq", "following_url": "https://api.github.com/users/paneq/following{/other_user}", "received_events_url": "https://api.github.com/users/paneq/received_events", "organizations_url": "https://api.github.com/users/paneq/orgs", "avatar_url": "https://0.gravatar.com/avatar/9b81cae1fb43808ac23a2188258ca9e4?d=https%3A%2F%2Fidenticons.github.com%2F180bb054f1a36e1777b05a0664a7eb71.png", "starred_url": "https://api.github.com/users/paneq/starred{/owner}{/repo}", "id": 65587, "followers_url": "https://api.github.com/users/paneq/followers", "type": "User"}, "created_at": "2012-07-12T22:25:37Z", "id": 6949677, "owner": "rails"}
