{"body": "1. I don't use transaction. Parent record is destroyed but child records still alive as zombie.\n2. I know some other way to resolve this problem. But I seem to be such destroy behavior(parent is destroyed but children is alive) is unnatural.", "url": "https://api.github.com/repos/rails/rails/issues/comments/7522595", "created_at": "2012-08-06T12:26:03Z", "html_url": "https://github.com/rails/rails/pull/7267#issuecomment-7522595", "updated_at": "2012-08-06T12:26:03Z", "repo": "rails", "issue_id": 7267, "user": {"following_url": "https://api.github.com/users/yalab/following{/other_user}", "events_url": "https://api.github.com/users/yalab/events{/privacy}", "organizations_url": "https://api.github.com/users/yalab/orgs", "url": "https://api.github.com/users/yalab", "gists_url": "https://api.github.com/users/yalab/gists{/gist_id}", "html_url": "https://github.com/yalab", "subscriptions_url": "https://api.github.com/users/yalab/subscriptions", "avatar_url": "https://2.gravatar.com/avatar/aa452bc2667982dabd920ce1af0d8710?d=https%3A%2F%2Fidenticons.github.com%2F003f23cd58011b471fba7b66fbfb2565.png", "repos_url": "https://api.github.com/users/yalab/repos", "received_events_url": "https://api.github.com/users/yalab/received_events", "gravatar_id": "aa452bc2667982dabd920ce1af0d8710", "starred_url": "https://api.github.com/users/yalab/starred{/owner}{/repo}", "login": "yalab", "type": "User", "id": 64558, "followers_url": "https://api.github.com/users/yalab/followers"}, "owner": "rails", "_id": {"$oid": "5237fdbbbd3543c15100bb98"}, "id": 7522595, "issue_url": "https://api.github.com/repos/rails/rails/issues/7267"}
