{"updated_at": "2012-08-24T15:59:13Z", "repo": "rails", "created_at": "2012-08-24T15:59:13Z", "owner": "rails", "url": "https://api.github.com/repos/rails/rails/issues/comments/8006165", "id": 8006165, "issue_url": "https://api.github.com/repos/rails/rails/issues/3750", "issue_id": 3750, "user": {"repos_url": "https://api.github.com/users/the8472/repos", "type": "User", "html_url": "https://github.com/the8472", "starred_url": "https://api.github.com/users/the8472/starred{/owner}{/repo}", "subscriptions_url": "https://api.github.com/users/the8472/subscriptions", "following_url": "https://api.github.com/users/the8472/following{/other_user}", "gravatar_id": "73c735c48c009e30be46512e9dc7f29a", "organizations_url": "https://api.github.com/users/the8472/orgs", "url": "https://api.github.com/users/the8472", "gists_url": "https://api.github.com/users/the8472/gists{/gist_id}", "avatar_url": "https://2.gravatar.com/avatar/73c735c48c009e30be46512e9dc7f29a?d=https%3A%2F%2Fidenticons.github.com%2F570ce0330acf4d9c41f71e343203c065.png", "id": 1065730, "events_url": "https://api.github.com/users/the8472/events{/privacy}", "login": "the8472", "received_events_url": "https://api.github.com/users/the8472/received_events", "followers_url": "https://api.github.com/users/the8472/followers"}, "body": "+1 to overriding new, right now a lot of magic breaks down when you use STI, this would fix a good part of it.", "_id": {"$oid": "52383250bd3543c15100f899"}, "html_url": "https://github.com/rails/rails/pull/3750#issuecomment-8006165"}
