{"body": "This is an issue for my team as well.  We use `test` env when testing on our own machines, but `ci-test` for our CI machine build, which has a different database setup (different adapters and all).  I don't understand why this issue is closed, as not everyone will be testing in the `test` env no matter what.", "url": "https://api.github.com/repos/rails/rails/issues/comments/9352606", "created_at": "2012-10-11T18:37:04Z", "html_url": "https://github.com/rails/rails/pull/5669#issuecomment-9352606", "updated_at": "2012-10-11T18:37:12Z", "repo": "rails", "issue_id": 5669, "user": {"following_url": "https://api.github.com/users/mhuggins/following{/other_user}", "events_url": "https://api.github.com/users/mhuggins/events{/privacy}", "organizations_url": "https://api.github.com/users/mhuggins/orgs", "url": "https://api.github.com/users/mhuggins", "gists_url": "https://api.github.com/users/mhuggins/gists{/gist_id}", "html_url": "https://github.com/mhuggins", "subscriptions_url": "https://api.github.com/users/mhuggins/subscriptions", "avatar_url": "https://1.gravatar.com/avatar/781f66c42983ae7ee3123bbd620d8568?d=https%3A%2F%2Fidenticons.github.com%2F8cc10a343f7cacddbbc5488786f3f22b.png", "repos_url": "https://api.github.com/users/mhuggins/repos", "received_events_url": "https://api.github.com/users/mhuggins/received_events", "gravatar_id": "781f66c42983ae7ee3123bbd620d8568", "starred_url": "https://api.github.com/users/mhuggins/starred{/owner}{/repo}", "login": "mhuggins", "type": "User", "id": 169093, "followers_url": "https://api.github.com/users/mhuggins/followers"}, "owner": "rails", "_id": {"$oid": "52381472bd3543c15100dba9"}, "id": 9352606, "issue_url": "https://api.github.com/repos/rails/rails/issues/5669"}
