{"issue_url": "https://api.github.com/repos/rails/rails/issues/5813", "repo": "rails", "body": "This needs a rebase.", "_id": {"$oid": "523ea094bd354364b901181f"}, "issue_id": 5813, "url": "https://api.github.com/repos/rails/rails/issues/comments/9871411", "html_url": "https://github.com/rails/rails/pull/5813#issuecomment-9871411", "updated_at": "2012-10-29T15:36:58Z", "user": {"subscriptions_url": "https://api.github.com/users/frodsan/subscriptions", "events_url": "https://api.github.com/users/frodsan/events{/privacy}", "repos_url": "https://api.github.com/users/frodsan/repos", "gists_url": "https://api.github.com/users/frodsan/gists{/gist_id}", "url": "https://api.github.com/users/frodsan", "login": "frodsan", "gravatar_id": "0cd9079e8f5b64c6e9b6a3ad2ade0a5e", "html_url": "https://github.com/frodsan", "following_url": "https://api.github.com/users/frodsan/following{/other_user}", "received_events_url": "https://api.github.com/users/frodsan/received_events", "organizations_url": "https://api.github.com/users/frodsan/orgs", "avatar_url": "https://2.gravatar.com/avatar/0cd9079e8f5b64c6e9b6a3ad2ade0a5e?d=https%3A%2F%2Fidenticons.github.com%2Faf707e4639c05d338a28b7e5321a865d.png", "starred_url": "https://api.github.com/users/frodsan/starred{/owner}{/repo}", "id": 840464, "followers_url": "https://api.github.com/users/frodsan/followers", "type": "User"}, "created_at": "2012-10-29T15:36:58Z", "id": 9871411, "owner": "rails"}
