{"issue_url": "https://api.github.com/repos/rails/rails/issues/265", "repo": "rails", "body": "+1 for removing `Object#among?`/`Object#either?`\n+1 for ernie's suggestion (so -1 for adding Object#ex?). We need no inverse for Object#in?, as we can simply use `!`/`not`/`unless`, as in:\n\n    unless my_object.in?([\"a\", \"b\", \"c\"])\n     ...\n    end\n\nor\n\n    if my_object.in?([\"a\", \"b\"]) and not my_object.in?([\"c\", \"d\"])\n      ...\n    end", "_id": {"$oid": "523863f1bd3543c151012536"}, "issue_id": 265, "url": "https://api.github.com/repos/rails/rails/issues/comments/994331", "html_url": "https://github.com/rails/rails/pull/265#issuecomment-994331", "updated_at": "2011-04-13T09:00:30Z", "user": {"subscriptions_url": "https://api.github.com/users/arthurschreiber/subscriptions", "events_url": "https://api.github.com/users/arthurschreiber/events{/privacy}", "repos_url": "https://api.github.com/users/arthurschreiber/repos", "gists_url": "https://api.github.com/users/arthurschreiber/gists{/gist_id}", "url": "https://api.github.com/users/arthurschreiber", "login": "arthurschreiber", "gravatar_id": "0a56b0d8f78a37d1a843e83144f3fa3c", "html_url": "https://github.com/arthurschreiber", "following_url": "https://api.github.com/users/arthurschreiber/following{/other_user}", "received_events_url": "https://api.github.com/users/arthurschreiber/received_events", "organizations_url": "https://api.github.com/users/arthurschreiber/orgs", "avatar_url": "https://0.gravatar.com/avatar/0a56b0d8f78a37d1a843e83144f3fa3c?d=https%3A%2F%2Fidenticons.github.com%2F8c5f6ecd29a0eb234459190ca51c16dd.png", "starred_url": "https://api.github.com/users/arthurschreiber/starred{/owner}{/repo}", "id": 2195, "followers_url": "https://api.github.com/users/arthurschreiber/followers", "type": "User"}, "created_at": "2011-04-13T08:57:52Z", "id": 994331, "owner": "rails"}
