{"issue_url": "https://api.github.com/repos/rails/rails/issues/343", "repo": "rails", "body": "@MDaubs Thanks, I can't wait for this to be released. I was about to fork it myself.", "_id": {"$oid": "523861d9bd3543c151012378"}, "issue_id": 343, "url": "https://api.github.com/repos/rails/rails/issues/comments/1164495", "html_url": "https://github.com/rails/rails/pull/343#issuecomment-1164495", "updated_at": "2011-05-15T01:17:47Z", "user": {"subscriptions_url": "https://api.github.com/users/nickradford/subscriptions", "events_url": "https://api.github.com/users/nickradford/events{/privacy}", "repos_url": "https://api.github.com/users/nickradford/repos", "gists_url": "https://api.github.com/users/nickradford/gists{/gist_id}", "url": "https://api.github.com/users/nickradford", "login": "nickradford", "gravatar_id": "396198e5e8afc42d2b40ccb55c2c5fdd", "html_url": "https://github.com/nickradford", "following_url": "https://api.github.com/users/nickradford/following{/other_user}", "received_events_url": "https://api.github.com/users/nickradford/received_events", "organizations_url": "https://api.github.com/users/nickradford/orgs", "avatar_url": "https://1.gravatar.com/avatar/396198e5e8afc42d2b40ccb55c2c5fdd?d=https%3A%2F%2Fidenticons.github.com%2F0269585bb565e99726fb9700dd418834.png", "starred_url": "https://api.github.com/users/nickradford/starred{/owner}{/repo}", "id": 222221, "followers_url": "https://api.github.com/users/nickradford/followers", "type": "User"}, "created_at": "2011-05-15T01:17:47Z", "id": 1164495, "owner": "rails"}
