{"body": "@willbryant I strongly disagree with reverting this,  however it's clearly broken things and we'll need to ship fixes which don't.\r\n\r\n'Only allowing JSON or XML' includes ~100% of applications, just because you're able to disable it and knew how doesn't mean others can or will and the consequences are too severe to just punt on it till 4.0 ships\r\n\r\nLet's make sure we fix the regressions so that we're only quoting when we *know* it's for a string column, but removing the quoting changes altogether isn't an option", "url": "https://api.github.com/repos/rails/rails/issues/comments/13415817", "created_at": "2013-02-12T02:49:51Z", "html_url": "https://github.com/rails/rails/pull/9207#issuecomment-13415817", "updated_at": "2013-02-12T02:49:51Z", "repo": "rails", "issue_id": 9207, "user": {"following_url": "https://api.github.com/users/NZKoz/following{/other_user}", "events_url": "https://api.github.com/users/NZKoz/events{/privacy}", "organizations_url": "https://api.github.com/users/NZKoz/orgs", "url": "https://api.github.com/users/NZKoz", "gists_url": "https://api.github.com/users/NZKoz/gists{/gist_id}", "html_url": "https://github.com/NZKoz", "subscriptions_url": "https://api.github.com/users/NZKoz/subscriptions", "avatar_url": "https://0.gravatar.com/avatar/efa76b164a7de4a5730e4fa397cc4425?d=https%3A%2F%2Fidenticons.github.com%2F85d8ce590ad8981ca2c8286f79f59954.png", "repos_url": "https://api.github.com/users/NZKoz/repos", "received_events_url": "https://api.github.com/users/NZKoz/received_events", "gravatar_id": "efa76b164a7de4a5730e4fa397cc4425", "starred_url": "https://api.github.com/users/NZKoz/starred{/owner}{/repo}", "login": "NZKoz", "type": "User", "id": 197, "followers_url": "https://api.github.com/users/NZKoz/followers"}, "owner": "rails", "_id": {"$oid": "5237ec25bd3543c151009c50"}, "id": 13415817, "issue_url": "https://api.github.com/repos/rails/rails/issues/9207"}
