{"issue_url": "https://api.github.com/repos/rails/rails/issues/9691", "repo": "rails", "body": "rebased and squashed /cc @steveklabnik ", "_id": {"$oid": "523d15afbd354364b900474a"}, "issue_id": 9691, "url": "https://api.github.com/repos/rails/rails/issues/comments/14955522", "html_url": "https://github.com/rails/rails/pull/9691#issuecomment-14955522", "updated_at": "2013-03-15T11:23:11Z", "user": {"subscriptions_url": "https://api.github.com/users/hone/subscriptions", "events_url": "https://api.github.com/users/hone/events{/privacy}", "repos_url": "https://api.github.com/users/hone/repos", "gists_url": "https://api.github.com/users/hone/gists{/gist_id}", "url": "https://api.github.com/users/hone", "login": "hone", "gravatar_id": "efb7c66871043330ce1310a9bdd0aaf6", "html_url": "https://github.com/hone", "following_url": "https://api.github.com/users/hone/following{/other_user}", "received_events_url": "https://api.github.com/users/hone/received_events", "organizations_url": "https://api.github.com/users/hone/orgs", "avatar_url": "https://1.gravatar.com/avatar/efb7c66871043330ce1310a9bdd0aaf6?d=https%3A%2F%2Fidenticons.github.com%2Fdde66d304fd8ae12981d9b5b290dd3bd.png", "starred_url": "https://api.github.com/users/hone/starred{/owner}{/repo}", "id": 16457, "followers_url": "https://api.github.com/users/hone/followers", "type": "User"}, "created_at": "2013-03-15T11:22:59Z", "id": 14955522, "owner": "rails"}
