{"updated_at": "2013-03-15T22:17:24Z", "repo": "rails", "created_at": "2013-03-15T22:17:24Z", "owner": "rails", "url": "https://api.github.com/repos/rails/rails/issues/comments/14987978", "id": 14987978, "issue_url": "https://api.github.com/repos/rails/rails/issues/9733", "issue_id": 9733, "user": {"repos_url": "https://api.github.com/users/sadfuzzy/repos", "type": "User", "html_url": "https://github.com/sadfuzzy", "starred_url": "https://api.github.com/users/sadfuzzy/starred{/owner}{/repo}", "subscriptions_url": "https://api.github.com/users/sadfuzzy/subscriptions", "following_url": "https://api.github.com/users/sadfuzzy/following{/other_user}", "gravatar_id": "4ae0551498812b89794e157f913c6e27", "organizations_url": "https://api.github.com/users/sadfuzzy/orgs", "url": "https://api.github.com/users/sadfuzzy", "gists_url": "https://api.github.com/users/sadfuzzy/gists{/gist_id}", "avatar_url": "https://2.gravatar.com/avatar/4ae0551498812b89794e157f913c6e27?d=https%3A%2F%2Fidenticons.github.com%2F1d1900d4a9f7c614b464e7d127d3aff6.png", "id": 158883, "events_url": "https://api.github.com/users/sadfuzzy/events{/privacy}", "login": "sadfuzzy", "received_events_url": "https://api.github.com/users/sadfuzzy/received_events", "followers_url": "https://api.github.com/users/sadfuzzy/followers"}, "body": "Great commit!", "_id": {"$oid": "5237e72cbd3543c151009526"}, "html_url": "https://github.com/rails/rails/pull/9733#issuecomment-14987978"}
