{"updated_at": "2013-03-18T18:33:54Z", "repo": "rails", "created_at": "2013-03-18T18:33:54Z", "owner": "rails", "url": "https://api.github.com/repos/rails/rails/issues/comments/15072847", "id": 15072847, "issue_url": "https://api.github.com/repos/rails/rails/issues/9022", "issue_id": 9022, "user": {"repos_url": "https://api.github.com/users/braddunbar/repos", "type": "User", "html_url": "https://github.com/braddunbar", "starred_url": "https://api.github.com/users/braddunbar/starred{/owner}{/repo}", "subscriptions_url": "https://api.github.com/users/braddunbar/subscriptions", "following_url": "https://api.github.com/users/braddunbar/following{/other_user}", "gravatar_id": "0168f51cd822a820c606c259b80e253f", "organizations_url": "https://api.github.com/users/braddunbar/orgs", "url": "https://api.github.com/users/braddunbar", "gists_url": "https://api.github.com/users/braddunbar/gists{/gist_id}", "avatar_url": "https://2.gravatar.com/avatar/0168f51cd822a820c606c259b80e253f?d=https%3A%2F%2Fidenticons.github.com%2Ffc50322932b29b26cfc46fd9a91ec474.png", "id": 11674, "events_url": "https://api.github.com/users/braddunbar/events{/privacy}", "login": "braddunbar", "received_events_url": "https://api.github.com/users/braddunbar/received_events", "followers_url": "https://api.github.com/users/braddunbar/followers"}, "body": "Ping!  @steveklabnik Anything else you need here?", "_id": {"$oid": "523d5d7cbd354364b90062c4"}, "html_url": "https://github.com/rails/rails/pull/9022#issuecomment-15072847"}
