{"issue_url": "https://api.github.com/repos/rails/rails/issues/8501", "repo": "rails", "body": "I agree with you guys. I think we should keep it. It's just a good thing to keep in mind that it'll probably break a lot of stuff.", "_id": {"$oid": "5237f29abd3543c15100a663"}, "issue_id": 8501, "url": "https://api.github.com/repos/rails/rails/issues/comments/15596995", "html_url": "https://github.com/rails/rails/pull/8501#issuecomment-15596995", "updated_at": "2013-03-28T16:04:48Z", "user": {"subscriptions_url": "https://api.github.com/users/jnicklas/subscriptions", "events_url": "https://api.github.com/users/jnicklas/events{/privacy}", "repos_url": "https://api.github.com/users/jnicklas/repos", "gists_url": "https://api.github.com/users/jnicklas/gists{/gist_id}", "url": "https://api.github.com/users/jnicklas", "login": "jnicklas", "gravatar_id": "6c469749d725177dd2837d806c769cd4", "html_url": "https://github.com/jnicklas", "following_url": "https://api.github.com/users/jnicklas/following{/other_user}", "received_events_url": "https://api.github.com/users/jnicklas/received_events", "organizations_url": "https://api.github.com/users/jnicklas/orgs", "avatar_url": "https://1.gravatar.com/avatar/6c469749d725177dd2837d806c769cd4?d=https%3A%2F%2Fidenticons.github.com%2F02522a2b2726fb0a03bb19f2d8d9524d.png", "starred_url": "https://api.github.com/users/jnicklas/starred{/owner}{/repo}", "id": 134, "followers_url": "https://api.github.com/users/jnicklas/followers", "type": "User"}, "created_at": "2013-03-28T16:04:48Z", "id": 15596995, "owner": "rails"}
