{"body": "What about oj and yajl support?", "url": "https://api.github.com/repos/rails/rails/issues/comments/17936232", "created_at": "2013-05-15T12:49:34Z", "html_url": "https://github.com/rails/rails/pull/10576#issuecomment-17936232", "updated_at": "2013-05-15T12:49:34Z", "repo": "rails", "issue_id": 10576, "user": {"following_url": "https://api.github.com/users/teamon/following{/other_user}", "events_url": "https://api.github.com/users/teamon/events{/privacy}", "organizations_url": "https://api.github.com/users/teamon/orgs", "url": "https://api.github.com/users/teamon", "gists_url": "https://api.github.com/users/teamon/gists{/gist_id}", "html_url": "https://github.com/teamon", "subscriptions_url": "https://api.github.com/users/teamon/subscriptions", "avatar_url": "https://2.gravatar.com/avatar/9fae8c5d475fe322a3a74e53d56ee2a0?d=https%3A%2F%2Fidenticons.github.com%2F20ef119e812e178ecb44efa448b57ebc.png", "repos_url": "https://api.github.com/users/teamon/repos", "received_events_url": "https://api.github.com/users/teamon/received_events", "gravatar_id": "9fae8c5d475fe322a3a74e53d56ee2a0", "starred_url": "https://api.github.com/users/teamon/starred{/owner}{/repo}", "login": "teamon", "type": "User", "id": 8083, "followers_url": "https://api.github.com/users/teamon/followers"}, "owner": "rails", "_id": {"$oid": "5237dd7ebd3543c151008afd"}, "id": 17936232, "issue_url": "https://api.github.com/repos/rails/rails/issues/10576"}
