{"updated_at": "2011-12-31T03:59:21Z", "repo": "rails", "created_at": "2011-12-31T03:59:21Z", "owner": "rails", "url": "https://api.github.com/repos/rails/rails/issues/comments/3319483", "id": 3319483, "issue_url": "https://api.github.com/repos/rails/rails/issues/2955", "issue_id": 2955, "user": {"repos_url": "https://api.github.com/users/dmitry/repos", "type": "User", "html_url": "https://github.com/dmitry", "starred_url": "https://api.github.com/users/dmitry/starred{/owner}{/repo}", "subscriptions_url": "https://api.github.com/users/dmitry/subscriptions", "following_url": "https://api.github.com/users/dmitry/following{/other_user}", "gravatar_id": "832ed6ace46d61032151f4e1864c057f", "organizations_url": "https://api.github.com/users/dmitry/orgs", "url": "https://api.github.com/users/dmitry", "gists_url": "https://api.github.com/users/dmitry/gists{/gist_id}", "avatar_url": "https://1.gravatar.com/avatar/832ed6ace46d61032151f4e1864c057f?d=https%3A%2F%2Fidenticons.github.com%2F237168031d88451c78fd8d6d6378c0b2.png", "id": 5091, "events_url": "https://api.github.com/users/dmitry/events{/privacy}", "login": "dmitry", "received_events_url": "https://api.github.com/users/dmitry/received_events", "followers_url": "https://api.github.com/users/dmitry/followers"}, "body": "Please include this fix. Thank you!", "_id": {"$oid": "52383d47bd3543c151010462"}, "html_url": "https://github.com/rails/rails/pull/2955#issuecomment-3319483"}
