{"body": "@carlosantoniodasilva So just fix the problem outlined at https://github.com/rails/rails/commit/302c912 and it's back in?\r\n\r\nDon't you think that removing it is a little drastic? Especially when the benefits it provides are incredible?\r\n\r\n@guilleiguaran can do.", "url": "https://api.github.com/repos/rails/rails/issues/comments/4586081", "created_at": "2012-03-19T23:23:39Z", "html_url": "https://github.com/rails/rails/pull/5261#issuecomment-4586081", "updated_at": "2012-03-19T23:23:39Z", "repo": "rails", "issue_id": 5261, "user": {"following_url": "https://api.github.com/users/sskirby/following{/other_user}", "events_url": "https://api.github.com/users/sskirby/events{/privacy}", "organizations_url": "https://api.github.com/users/sskirby/orgs", "url": "https://api.github.com/users/sskirby", "gists_url": "https://api.github.com/users/sskirby/gists{/gist_id}", "html_url": "https://github.com/sskirby", "subscriptions_url": "https://api.github.com/users/sskirby/subscriptions", "avatar_url": "https://0.gravatar.com/avatar/4d4c378e3a10e2d01a636a33c359734c?d=https%3A%2F%2Fidenticons.github.com%2F6f3e24662182e125fc58299809ee6a67.png", "repos_url": "https://api.github.com/users/sskirby/repos", "received_events_url": "https://api.github.com/users/sskirby/received_events", "gravatar_id": "4d4c378e3a10e2d01a636a33c359734c", "starred_url": "https://api.github.com/users/sskirby/starred{/owner}{/repo}", "login": "sskirby", "type": "User", "id": 25760, "followers_url": "https://api.github.com/users/sskirby/followers"}, "owner": "rails", "_id": {"$oid": "523ed417bd354364b9013208"}, "id": 4586081, "issue_url": "https://api.github.com/repos/rails/rails/issues/5261"}
