{"body": "It's true. Seems like these methods were always protected. And it's possible to call it from a controller or view.\r\n\r\n\r\nIn **3rd** commit adds test for this method, but that was not actually the place where it appeared.\r\n**1st** and **2nd** commit looks like a followups.\r\nBefore these commits it seems like this method had a different API - see **4th**. It's hard to track.\r\n\r\nThe code itself looks almost in the same way as in 2006.\r\n\r\nI personally don't feel like this is something people relay on in apps.\r\nCan't imagine the use case when this method can be called from controller or a view.\r\n\r\n\r\n**1st**\r\ncommit 8c4b599b7c62b85069fa04533e8f06e5476f927a\r\nAuthor: Rick Olson <technoweenie@gmail.com>\r\nDate:   Sun Aug 13 18:31:58 2006 +0000\r\n\r\n    Fix assert_redirected_to issue with named routes for module controllers.  [Rick Olson]\r\n\r\n**2nd**\r\ncommit e494b0a441aab6d85a7b1cdc2c3b0d03196ada21\r\nAuthor: Nicholas Seckar <nseckar@gmail.com>\r\nDate:   Fri Jun 30 02:36:17 2006 +0000\r\n\r\n    Add route_name_path method to generate only the path for a named routes. For example, map.person will add person_path.\r\n\r\n\r\n\r\n**3rd**\r\ncommit b20c575ac02373723438468932ceddd97056c9ec\r\nAuthor: Jamis Buck <jamis@37signals.com>\r\nDate:   Thu Jun 1 15:42:08 2006 +0000\r\n\r\n    New routes implementation. Simpler, faster, easier to understand. The published API for config/routes.rb is unchanged, but nearly everything else is different, so e\r\n    \r\n**4th**\r\ncommit 8e56f5ea3e5394caa2ffee466a7395876c288c2a\r\nAuthor: David Heinemeier Hansson <david@loudthinking.com>\r\nDate:   Fri Jun 24 16:40:01 2005 +0000\r\n\r\n    Improved performance of Routes generation by a factor of 5 #1434 [Nicholas Seckar] Added named routes (NEEDS BETTER DESCRIPTION) #1434 [Nicholas Seckar]\r\n\r\n", "url": "https://api.github.com/repos/rails/rails/issues/comments/5327275", "created_at": "2012-04-25T09:19:23Z", "html_url": "https://github.com/rails/rails/pull/5962#issuecomment-5327275", "updated_at": "2012-04-25T09:19:23Z", "repo": "rails", "issue_id": 5962, "user": {"following_url": "https://api.github.com/users/bogdan/following{/other_user}", "events_url": "https://api.github.com/users/bogdan/events{/privacy}", "organizations_url": "https://api.github.com/users/bogdan/orgs", "url": "https://api.github.com/users/bogdan", "gists_url": "https://api.github.com/users/bogdan/gists{/gist_id}", "html_url": "https://github.com/bogdan", "subscriptions_url": "https://api.github.com/users/bogdan/subscriptions", "avatar_url": "https://2.gravatar.com/avatar/91913f6ab8085bab0f2aa43995ba8ca2?d=https%3A%2F%2Fidenticons.github.com%2F926d19e70f74c20f796d376aafa3c6e2.png", "repos_url": "https://api.github.com/users/bogdan/repos", "received_events_url": "https://api.github.com/users/bogdan/received_events", "gravatar_id": "91913f6ab8085bab0f2aa43995ba8ca2", "starred_url": "https://api.github.com/users/bogdan/starred{/owner}{/repo}", "login": "bogdan", "type": "User", "id": 122436, "followers_url": "https://api.github.com/users/bogdan/followers"}, "owner": "rails", "_id": {"$oid": "523810c2bd3543c15100d700"}, "id": 5327275, "issue_url": "https://api.github.com/repos/rails/rails/issues/5962"}
