{"updated_at": "2012-10-09T20:56:36Z", "repo": "rails", "created_at": "2012-10-09T20:56:36Z", "owner": "rails", "url": "https://api.github.com/repos/rails/rails/issues/comments/9279507", "id": 9279507, "issue_url": "https://api.github.com/repos/rails/rails/issues/7878", "issue_id": 7878, "user": {"repos_url": "https://api.github.com/users/justinko/repos", "type": "User", "html_url": "https://github.com/justinko", "starred_url": "https://api.github.com/users/justinko/starred{/owner}{/repo}", "subscriptions_url": "https://api.github.com/users/justinko/subscriptions", "following_url": "https://api.github.com/users/justinko/following{/other_user}", "gravatar_id": "1df9fc8ddf084661265bbae74a8d0b43", "organizations_url": "https://api.github.com/users/justinko/orgs", "url": "https://api.github.com/users/justinko", "gists_url": "https://api.github.com/users/justinko/gists{/gist_id}", "avatar_url": "https://2.gravatar.com/avatar/1df9fc8ddf084661265bbae74a8d0b43?d=https%3A%2F%2Fidenticons.github.com%2F11084aaf0a5fc9561425a254a219f6f6.png", "id": 14007, "events_url": "https://api.github.com/users/justinko/events{/privacy}", "login": "justinko", "received_events_url": "https://api.github.com/users/justinko/received_events", "followers_url": "https://api.github.com/users/justinko/followers"}, "body": "Ah, yes, for some reason my brain thought \"integration\" was taken. I change my vote from \"requests\" to \"integration\". \r\n\r\nYou are running a test that \"integrates\" parts of the system from the highest level available. Self explanatory.", "_id": {"$oid": "5237f7febd3543c15100b19f"}, "html_url": "https://github.com/rails/rails/pull/7878#issuecomment-9279507"}
